predictive_tools/__init__.py
predictive_tools/predict.py
predictive_analytic-0.0.4.dist-info/LICENSE
predictive_analytic-0.0.4.dist-info/METADATA
predictive_analytic-0.0.4.dist-info/WHEEL
predictive_analytic-0.0.4.dist-info/top_level.txt
predictive_analytic-0.0.4.dist-info/RECORD
